image_analyst/onnx/__init__.py
image_analyst/onnx/models.py
image_analyst_onnx-0.2.0.dist-info/LICENSE
image_analyst_onnx-0.2.0.dist-info/METADATA
image_analyst_onnx-0.2.0.dist-info/WHEEL
image_analyst_onnx-0.2.0.dist-info/RECORD
