Metadata-Version: 2.1
Name: image-analyst-onnx
Version: 0.2.0
Summary: ImageAnalyst ONNX is an extension to the ImageAnalyst library, providing additional models and functions using onnx.
Home-page: https://github.com/BergLucas/ImageAnalystONNX
Keywords: image,analysis,onnx
Author: Lucas Berg
Author-email: 55436804+BergLucas@users.noreply.github.com
Requires-Python: >=3.9,<4.0
Classifier: Development Status :: 3 - Alpha
Classifier: License :: OSI Approved :: MIT License
Classifier: Programming Language :: Python :: 3
Classifier: Programming Language :: Python :: 3.9
Classifier: Programming Language :: Python :: 3.10
Classifier: Programming Language :: Python :: 3.11
Requires-Dist: image-analyst (>=0.2.0,<0.3.0)
Requires-Dist: numpy (>=1.24.3,<2.0.0)
Requires-Dist: onnxruntime (>=1.15.1,<2.0.0)
Project-URL: Repository, https://github.com/BergLucas/ImageAnalystONNX
